Analysis/EntropyBinning.py
Analysis/__init__.py
EntropyBinning-0.1.3.2.dist-info/METADATA
EntropyBinning-0.1.3.2.dist-info/WHEEL
EntropyBinning-0.1.3.2.dist-info/top_level.txt
EntropyBinning-0.1.3.2.dist-info/RECORD
