Metadata-Version: 2.1
Name: EntropyBinning
Version: 0.1.3.2
Summary: Entropy base binning for data analysis
Author: chingDev.Official (Prince Carl Ajoc)
Author-email: chingace471@gmail.com
Keywords: python,video,stream,video stream,camera stream,sockets
Classifier: Development Status :: 1 - Planning
Classifier: Intended Audience :: Developers
Classifier: Programming Language :: Python :: 3
Classifier: Operating System :: Unix
Classifier: Operating System :: MacOS :: MacOS X
Classifier: Operating System :: Microsoft :: Windows
Requires-Dist: numpy
Requires-Dist: pandas
